bitcoinaddress/__init__.py
bitcoinaddress/address.py
bitcoinaddress/segwit_addr.py
bitcoinaddress/util.py
bitcoinaddress/wallet.py
bitcoinaddress/key/__init__.py
bitcoinaddress/key/key.py
bitcoinaddress/key/seed.py
bitcoinaddress-0.1.5.dist-info/LICENSE
bitcoinaddress-0.1.5.dist-info/METADATA
bitcoinaddress-0.1.5.dist-info/WHEEL
bitcoinaddress-0.1.5.dist-info/top_level.txt
bitcoinaddress-0.1.5.dist-info/RECORD
