Metadata-Version: 2.1
Name: bitcoinaddress
Version: 0.1.5
Summary: A simple Bitcoin address generator
Home-page: https://github.com/fortesp/bitcoinaddress
Author: Pedro Fortes
Author-email: pedro.daniel.g@gmail.com
License: UNKNOWN
Platform: UNKNOWN
Classifier: Programming Language :: Python :: 3
Classifier: License :: OSI Approved :: MIT License
Classifier: Operating System :: OS Independent
Requires-Python: >=3.6
Requires-Dist: base58
Requires-Dist: ecdsa
